time_logger/__init__.py
time_logger/profile.py
pytime_logger-0.0.4.dist-info/LICENSE
pytime_logger-0.0.4.dist-info/METADATA
pytime_logger-0.0.4.dist-info/WHEEL
pytime_logger-0.0.4.dist-info/top_level.txt
pytime_logger-0.0.4.dist-info/RECORD
