Metadata-Version: 2.1
Name: pytime-logger
Version: 0.0.4
Summary: This project provides a simple way to profile the execution time of your Python functions.
Author-email: Amir Pourmand <pourmand1376@gmail.com>
License: MIT License
Project-URL: Homepage, https://github.com/pourmand1376/time-logger/
Project-URL: Bug Tracker, https://github.com/pourmand1376/time-logger/issues
Classifier: Programming Language :: Python :: 3
Classifier: License :: OSI Approved :: MIT License
Classifier: Operating System :: OS Independent
Requires-Python: >=3.0
License-File: LICENSE
